hat/juggler/server.py
hat/juggler/__init__.py
hat/juggler/transport.py
hat/juggler/basic_auth.py
hat/juggler/client.py
hat_juggler-0.7.1.dist-info/LICENSE
hat_juggler-0.7.1.dist-info/METADATA
hat_juggler-0.7.1.dist-info/WHEEL
hat_juggler-0.7.1.dist-info/RECORD
