Metadata-Version: 2.1
Name: hat-juggler
Version: 0.7.1
Summary: Hat Juggler protocol
License: Apache-2.0
Classifier: Programming Language :: Python :: 3
Classifier: License :: OSI Approved :: Apache Software License
Provides-Extra: dev
Requires-Dist: aiohttp ~=3.10.11
Requires-Dist: hat-aio ~=0.7.12
Requires-Dist: hat-json ~=0.6.2
Requires-Dist: hat-util ~=0.6.19
Requires-Dist: hat-doit ~=0.16.2; extra == 'dev'
Requires-Python: >=3.10
Project-URL: Homepage, http://hat-open.com
Project-URL: Repository, https://github.com/hat-open/hat-juggler.git
Project-URL: Documentation, http://hat-juggler.hat-open.com
